LRFutils/__init__.py
LRFutils/archive.py
LRFutils/color.py
LRFutils/logs.py
LRFutils/progress.py
LRFutils/term.py
LRFutils-0.1.2.dist-info/LICENSE
LRFutils-0.1.2.dist-info/METADATA
LRFutils-0.1.2.dist-info/WHEEL
LRFutils-0.1.2.dist-info/top_level.txt
LRFutils-0.1.2.dist-info/RECORD
