Metadata-Version: 2.1
Name: LRFutils
Version: 0.1.2
Summary: Just a custom library to share with some colleagues. Use it at your own risks.
Author-email: Leirof <vince.lrf@gmail.com>
Project-URL: Homepage, https://github.com/LeiRoF/LRFutils
Project-URL: Bug Tracker, https://github.com/LeiRoF/LRFutils/issues
Classifier: Programming Language :: Python :: 3
Classifier: License :: OSI Approved :: MIT License
Classifier: Operating System :: OS Independent
Requires-Python: >=3.7
License-File: LICENSE
